neon_users_service/__init__.py
neon_users_service/__main__.py
neon_users_service/default_config.yaml
neon_users_service/exceptions.py
neon_users_service/mq_connector.py
neon_users_service/service.py
neon_users_service/databases/__init__.py
neon_users_service/databases/mongodb.py
neon_users_service/databases/sqlite.py
neon_users_service-0.0.1a5.dist-info/LICENSE.md
neon_users_service-0.0.1a5.dist-info/METADATA
neon_users_service-0.0.1a5.dist-info/WHEEL
neon_users_service-0.0.1a5.dist-info/entry_points.txt
neon_users_service-0.0.1a5.dist-info/top_level.txt
neon_users_service-0.0.1a5.dist-info/zip-safe
neon_users_service-0.0.1a5.dist-info/RECORD
