Metadata-Version: 2.1
Name: neon-users-service
Version: 0.0.1a5
Summary: Neon User Management Module
Home-page: https://github.com/NeonGeckoCom/neon-users-service
Author: Neongecko
Author-email: developers@neon.ai
License: AGPL-3.0-only
Classifier: Intended Audience :: Developers
Classifier: Programming Language :: Python :: 3
License-File: LICENSE.md
Requires-Dist: pydantic~=2.0
Requires-Dist: ovos-config~=0.1
Requires-Dist: ovos-utils~=0.0
Requires-Dist: neon-data-models>=0.0.0a4
Requires-Dist: neon-utils[sentry]>=1.12.2a2,~=1.0
Provides-Extra: mongodb
Requires-Dist: pymongo~=4.0; extra == "mongodb"
Provides-Extra: mq
Requires-Dist: neon-mq-connector>=0.8.1a3,~=0.8; extra == "mq"
Provides-Extra: test
Requires-Dist: pytest; extra == "test"
Requires-Dist: mock; extra == "test"
